{
    "ban":{
        "user_noperms":"Ваша роль должна иметь права `BAN_MEMBERS` чтоб выполнить данную команду👺",
        "me_noperms":"Моя роль должна иметь права `BAN_MEMBERS` чтоб выполнить данную команду👺",
        "no_member":"Укажите пользователя которого хотите заблокировать на данном сервере",
        "owner":"Зачем овнера банить??? 👺",
        "admin":"За что банить админа???👺 ",
        "ok":{
            "action":"Участник был забанен",
            "moder":"Модератор: **{{moder.tag}}**",
            "member":"Заблокировал: **{{member.tag}}**",
            "reason":"По причине: `{{ban.reason}}`"
        }
    },
    "kick":{
        "user_noperms":"Ваша роль должна иметь права `KICK_MEMBERS` чтоб выполнить данную команду👺",
        "me_noperms":"Моя роль должна иметь права `KICK_MEMBERS` чтоб выполнить данную команду👺",
        "no_member":"Укажите пользователя которого хотите кикнуть на данном сервере",
        "owner":"Зачем овнера кикать??? 👺👺👺",
        "admin":"За что кикать админа???👺 ",
        "ok":{
            "action":"Участник был кикнут",
            "moder":"Модератор: **{{moder.tag}}**",
            "member":"Кикнул: **{{member.tag}}**",
            "reason":"По причине: `{{kick.reason}}`"
        }
    },
    "clear":{
        "user_noperms":"Ваша роль должна иметь права `MANAGE_MESSAGES` чтоб выполнить данную команду👺",
        "me_noperms":"Моя роль должна иметь права `MANAGE_MESSAGES` чтоб выполнить данную команду👺",
        "no_number":"Укажите количество сообщений для удаления",
        "yzpezno":"Удалено сообщений: `{{messages.count}}`"
    }
}